flask_twilio.py
Flask_Twilio-0.0.6.dist-info/DESCRIPTION.rst
Flask_Twilio-0.0.6.dist-info/METADATA
Flask_Twilio-0.0.6.dist-info/RECORD
Flask_Twilio-0.0.6.dist-info/WHEEL
Flask_Twilio-0.0.6.dist-info/metadata.json
Flask_Twilio-0.0.6.dist-info/top_level.txt
